19-NCO_LUT/lut.v
module lut #(
    parameter ADDR_BITS = 10
)(
    input wire [ADDR_BITS-1:0] addr_in,
    output wire [11:0] data_out
);
    reg [11:0] LUT [0:1023]; // 1024 valores de 12 bits

    initial begin
        $readmemh("sine_table.hex", LUT);
    end

    assign data_out = LUT[addr_in];

endmodule

19-NCO_LUT/nco.v
module nco #(
    parameter NCO_BITS = 10,
    parameter NCO_FREQ_BITS = 4 // Number of bits for frequency control word
)(
    input wire rst_in,
    input wire clk_in,
    input wire [NCO_FREQ_BITS-1:0] fcw_in, // Frequency control word input
    output wire [NCO_BITS-1:0] nco_out
);
    reg [NCO_BITS-1:0] nco_cnt;

    always @ (posedge clk_in or posedge rst_in) begin
        if (rst_in) begin
            nco_cnt <= {NCO_BITS{1'b0}};
        end else begin
            nco_cnt <= nco_cnt + fcw_in; // Increment NCO output by frequency control word
        end
    end

    assign nco_out = nco_cnt;

endmodule

19-NCO_LUT/top.v
`include "nco.v"
`include "lut.v"


module top (
    input wire clk_in,
    input wire rst_in,
    input wire [3:0] fcw_in, // Frequency control word input
    output wire [11:0] data_out
);

    wire [9:0] nco_out;

    // Instancia del NCO
    nco #(
        .NCO_BITS(10),
        .NCO_FREQ_BITS(4)
    ) nco_inst (
        .rst_in(rst_in),
        .clk_in(clk_in),
        .fcw_in(fcw_in),
        .nco_out(nco_out)
    );

    // Instancia de la LUT
    lut #(
        .ADDR_BITS(10)
    ) lut_inst (
        .addr_in(nco_out),
        .data_out(data_out)
    );

endmodule

19-NCO_LUT/top_tb.v
`include "top.v"
`timescale 1ns / 1ps


module top_tb #(
    parameter NCO_BITS = 12,
    parameter NCO_FREQ_BITS = 4 // Number of bits for frequency control word
);

    reg clk_in = 0;
    reg rst_in;
    reg [NCO_FREQ_BITS-1:0] fcw_in;
    wire [NCO_BITS-1:0] data_out;

    top dut (
        .clk_in(clk_in),
        .rst_in(rst_in),
        .fcw_in(fcw_in),
        .data_out(data_out)
    );

    initial begin
        $dumpfile("top.vcd");
        $dumpvars(0, top_tb);
    end

    always #10 clk_in = ~clk_in;
    initial begin
        // Initialize signals
        rst_in = 1;
        fcw_in = {NCO_FREQ_BITS{1'b0}};

        #20 rst_in = 0; // Release reset

        #20 fcw_in = 4'b0001; // Set frequency control word

        #100000 $finish; // End simulation
    end
endmodule

19-NCO_LUT/top.vcd
$date
	Mon Sep 15 15:31:50 2025
$end
$version
	Icarus Verilog
$end
$timescale
	1ps
$end
$scope module top_tb $end
$var wire 12 ! data_out [11:0] $end
$var reg 1 " clk_in $end
$var reg 4 # fcw_in [3:0] $end
$var reg 1 $ rst_in $end
$scope module dut $end
$var wire 1 " clk_in $end
$var wire 4 % fcw_in [3:0] $end
$var wire 1 $ rst_in $end
$var wire 10 & nco_out [9:0] $end
$var wire 12 ' data_out [11:0] $end
$scope module lut_inst $end
$var wire 12 ( data_out [11:0] $end
$var wire 10 ) addr_in [9:0] $end
$upscope $end
$scope module nco_inst $end
$var wire 1 " clk_in $end
$var wire 4 * fcw_in [3:0] $end
$var wire 10 + nco_out [9:0] $end
$var wire 1 $ rst_in $end
$var reg 10 , nco_cnt [9:0] $end
$upscope $end
$upscope $end
$upscope $end
$enddefinitions $end
#0
$dumpvars
b0 ,
b0 +
b0 *
b0 )
b100000000000 (
b100000000000 '
b0 &
b0 %
1$
b0 #
0"
b100000000000 !
$end
#10000
1"
#20000
0"
0$
#30000
1"
#40000
0"
b1 #
b1 %
b1 *
#50000
b100000001100 !
b100000001100 '
b100000001100 (
b1 &
b1 )
b1 +
b1 ,
1"
#60000
0"
#70000
b100000011001 !
b100000011001 '
b100000011001 (
b10 &
b10 )
b10 +
b10 ,
1"
#80000
0"
#90000
b100000100101 !
b100000100101 '
b100000100101 (
b11 &
b11 )
b11 +
b11 ,
1"
#100000
0"
#110000
b100000110010 !
b100000110010 '
b100000110010 (
b100 &
b100 )
b100 +
b100 ,
1"
#120000
0"
#130000
b100000111110 !
b100000111110 '
b100000111110 (
b101 &
b101 )
b101 +
b101 ,
1"
#140000
0"
#150000
b100001001011 !
b100001001011 '
b100001001011 (
b110 &
b110 )
b110 +
b110 ,
1"
#160000
0"
#170000
b100001010111 !
b100001010111 '
b100001010111 (
b111 &
b111 )
b111 +
b111 ,
1"
#180000
0"
#190000
b100001100100 !
b100001100100 '
b100001100100 (
b1000 &
b1000 )
b1000 +
b1000 ,
1"
#200000
0"
#210000
b100001110001 !
b100001110001 '
b100001110001 (
b1001 &
b1001 )
b1001 +
b1001 ,
1"
#220000
0"
#230000
b100001111101 !
b100001111101 '
b100001111101 (
b1010 &
b1010 )
b1010 +
b1010 ,
1"
#240000
0"
#250000
b100010001010 !
b100010001010 '
b100010001010 (
b1011 &
b1011 )
b1011 +
b1011 ,
1"
#260000
0"
#270000
b100010010110 !
b100010010110 '
b100010010110 (
b1100 &
b1100 )
b1100 +
b1100 ,
1"
#280000
0"
#290000
b100010100011 !
b100010100011 '
b100010100011 (
b1101 &
b1101 )
b1101 +
b1101 ,
1"
#300000
0"
#310000
b100010101111 !
b100010101111 '
b100010101111 (
b1110 &
b1110 )
b1110 +
b1110 ,
1"
#320000
0"
#330000
b100010111100 !
b100010111100 '
b100010111100 (
b1111 &
b1111 )
b1111 +
b1111 ,
1"
#340000
0"
#350000
b100011001000 !
b100011001000 '
b100011001000 (
b10000 &
b10000 )
b10000 +
b10000 ,
1"
#360000
0"
#370000
b100011010101 !
b100011010101 '
b100011010101 (
b10001 &
b10001 )
b10001 +
b10001 ,
1"
#380000
0"
#390000
b100011100001 !
b100011100001 '
b100011100001 (
b10010 &
b10010 )
b10010 +
b10010 ,
1"
#400000
0"
#410000
b100011101110 !
b100011101110 '
b100011101110 (
b10011 &
b10011 )
b10011 +
b10011 ,
1"
#420000
0"
#430000
b100011111010 !
b100011111010 '
b100011111010 (
b10100 &
b10100 )
b10100 +
b10100 ,
1"
#440000
0"
#450000
b100100000111 !
b100100000111 '
b100100000111 (
b10101 &
b10101 )
b10101 +
b10101 ,
1"
#460000
0"
#470000
b100100010011 !
b100100010011 '
b100100010011 (
b10110 &
b10110 )
b10110 +
b10110 ,
1"
#480000
0"
#490000
b100100011111 !
b100100011111 '
b100100011111 (
b10111 &
b10111 )
b10111 +
b10111 ,
1"
#500000
0"
#510000
b100100101100 !
b100100101100 '
b100100101100 (
b11000 &
b11000 )
b11000 +
b11000 ,
1"
#520000
0"
#530000
b100100111000 !
b100100111000 '
b100100111000 (
b11001 &
b11001 )
b11001 +
b11001 ,
1"
#540000
0"
#550000
b100101000101 !
b100101000101 '
b100101000101 (
b11010 &
b11010 )
b11010 +
b11010 ,
1"
#560000
0"
#570000
b100101010001 !
b100101010001 '
b100101010001 (
b11011 &
b11011 )
b11011 +
b11011 ,
1"
#580000
0"
#590000
b100101011110 !
b100101011110 '
b100101011110 (
b11100 &
b11100 )
b11100 +
b11100 ,
1"
#600000
0"
#610000
b100101101010 !
b100101101010 '
b100101101010 (
b11101 &
b11101 )
b11101 +
b11101 ,
1"
#620000
0"
#630000
b100101110110 !
b100101110110 '
b100101110110 (
b11110 &
b11110 )
b11110 +
b11110 ,
1"
#640000
0"
#650000
b100110000011 !
b100110000011 '
b100110000011 (
b11111 &
b11111 )
b11111 +
b11111 ,
1"
#660000
0"
#670000
b100110001111 !
b100110001111 '
b100110001111 (
b100000 &
b100000 )
b100000 +
b100000 ,
1"
#680000
0"
#690000
b100110011011 !
b100110011011 '
b100110011011 (
b100001 &
b100001 )
b100001 +
b100001 ,
1"
#700000
0"
#710000
b100110101000 !
b100110101000 '
b100110101000 (
b100010 &
b100010 )
b100010 +
b100010 ,
1"
#720000
0"
#730000
b100110110100 !
b100110110100 '
b100110110100 (
b100011 &
b100011 )
b100011 +
b100011 ,
1"
#740000
0"
#750000
b100111000000 !
b100111000000 '
b100111000000 (
b100100 &
b100100 )
b100100 +
b100100 ,
1"
#760000
0"
#770000
b100111001100 !
b100111001100 '
b100111001100 (
b100101 &
b100101 )
b100101 +
b100101 ,
1"
#780000
0"
#790000
b100111011001 !
b100111011001 '
b100111011001 (
b100110 &
b100110 )
b100110 +
b100110 ,
1"
#800000
0"
#810000
b100111100101 !
b100111100101 '
b100111100101 (
b100111 &
b100111 )
b100111 +
b100111 ,
1"
#820000
0"
#830000
b100111110001 !
b100111110001 '
b100111110001 (
b101000 &
b101000 )
b101000 +
b101000 ,
1"
#840000
0"
#850000
b100111111101 !
b100111111101 '
b100111111101 (
b101001 &
b101001 )
b101001 +
b101001 ,
1"
#860000
0"
#870000
b101000001001 !
b101000001001 '
b101000001001 (
b101010 &
b101010 )
b101010 +
b101010 ,
1"
#880000
0"
#890000
b101000010101 !
b101000010101 '
b101000010101 (
b101011 &
b101011 )
b101011 +
b101011 ,
1"
#900000
0"
#910000
b101000100010 !
b101000100010 '
b101000100010 (
b101100 &
b101100 )
b101100 +
b101100 ,
1"
#920000
0"
#930000
b101000101110 !
b101000101110 '
b101000101110 (
b101101 &
b101101 )
b101101 +
b101101 ,
1"
#940000
0"
#950000
b101000111010 !
b101000111010 '
b101000111010 (
b101110 &
b101110 )
b101110 +
b101110 ,
1"
#960000
0"
#970000
b101001000110 !
b101001000110 '
b101001000110 (
b101111 &
b101111 )
b101111 +
b101111 ,
1"
#980000
0"
#990000
b101001010010 !
b101001010010 '
b101001010010 (
b110000 &
b110000 )
b110000 +
b110000 ,
1"
#1000000
0"
#1010000
b101001011110 !
b101001011110 '
b101001011110 (
b110001 &
b110001 )
b110001 +
b110001 ,
1"
#1020000
0"
#1030000
b101001101010 !
b101001101010 '
b101001101010 (
b110010 &
b110010 )
b110010 +
b110010 ,
1"
#1040000
0"
#1050000
b101001110110 !
b101001110110 '
b101001110110 (
b110011 &
b110011 )
b110011 +
b110011 ,
1"
#1060000
0"
#1070000
b101010000010 !
b101010000010 '
b101010000010 (
b110100 &
b110100 )
b110100 +
b110100 ,
1"
#1080000
0"
#1090000
b101010001110 !
b101010001110 '
b101010001110 (
b110101 &
b110101 )
b110101 +
b110101 ,
1"
#1100000
0"
#1110000
b101010011010 !
b101010011010 '
b101010011010 (
b110110 &
b110110 )
b110110 +
b110110 ,
1"
#1120000
0"
#1130000
b101010100101 !
b101010100101 '
b101010100101 (
b110111 &
b110111 )
b110111 +
b110111 ,
1"
#1140000
0"
#1150000
b101010110001 !
b101010110001 '
b101010110001 (
b111000 &
b111000 )
b111000 +
b111000 ,
1"
#1160000
0"
#1170000
b101010111101 !
b101010111101 '
b101010111101 (
b111001 &
b111001 )
b111001 +
b111001 ,
1"
#1180000
0"
#1190000
b101011001001 !
b101011001001 '
b101011001001 (
b111010 &
b111010 )
b111010 +
b111010 ,
1"
#1200000
0"
#1210000
b101011010101 !
b101011010101 '
b101011010101 (
b111011 &
b111011 )
b111011 +
b111011 ,
1"
#1220000
0"
#1230000
b101011100000 !
b101011100000 '
b101011100000 (
b111100 &
b111100 )
b111100 +
b111100 ,
1"
#1240000
0"
#1250000
b101011101100 !
b101011101100 '
b101011101100 (
b111101 &
b111101 )
b111101 +
b111101 ,
1"
#1260000
0"
#1270000
b101011111000 !
b101011111000 '
b101011111000 (
b111110 &
b111110 )
b111110 +
b111110 ,
1"
#1280000
0"
#1290000
b101100000011 !
b101100000011 '
b101100000011 (
b111111 &
b111111 )
b111111 +
b111111 ,
1"
#1300000
0"
#1310000
b101100001111 !
b101100001111 '
b101100001111 (
b1000000 &
b1000000 )
b1000000 +
b1000000 ,
1"
#1320000
0"
#1330000
b101100011011 !
b101100011011 '
b101100011011 (
b1000001 &
b1000001 )
b1000001 +
b1000001 ,
1"
#1340000
0"
#1350000
b101100100110 !
b101100100110 '
b101100100110 (
b1000010 &
b1000010 )
b1000010 +
b1000010 ,
1"
#1360000
0"
#1370000
b101100110010 !
b101100110010 '
b101100110010 (
b1000011 &
b1000011 )
b1000011 +
b1000011 ,
1"
#1380000
0"
#1390000
b101100111101 !
b101100111101 '
b101100111101 (
b1000100 &
b1000100 )
b1000100 +
b1000100 ,
1"
#1400000
0"
#1410000
b101101001001 !
b101101001001 '
b101101001001 (
b1000101 &
b1000101 )
b1000101 +
b1000101 ,
1"
#1420000
0"
#1430000
b101101010100 !
b101101010100 '
b101101010100 (
b1000110 &
b1000110 )
b1000110 +
b1000110 ,
1"
#1440000
0"
#1450000
b101101100000 !
b101101100000 '
b101101100000 (
b1000111 &
b1000111 )
b1000111 +
b1000111 ,
1"
#1460000
0"
#1470000
b101101101011 !
b101101101011 '
b101101101011 (
b1001000 &
b1001000 )
b1001000 +
b1001000 ,
1"
#1480000
0"
#1490000
b101101110110 !
b101101110110 '
b101101110110 (
b1001001 &
b1001001 )
b1001001 +
b1001001 ,
1"
#1500000
0"
#1510000
b101110000010 !
b101110000010 '
b101110000010 (
b1001010 &
b1001010 )
b1001010 +
b1001010 ,
1"
#1520000
0"
#1530000
b101110001101 !
b101110001101 '
b101110001101 (
b1001011 &
b1001011 )
b1001011 +
b1001011 ,
1"
#1540000
0"
#1550000
b101110011000 !
b101110011000 '
b101110011000 (
b1001100 &
b1001100 )
b1001100 +
b1001100 ,
1"
#1560000
0"
#1570000
b101110100011 !
b101110100011 '
b101110100011 (
b1001101 &
b1001101 )
b1001101 +
b1001101 ,
1"
#1580000
0"
#1590000
b101110101110 !
b101110101110 '
b101110101110 (
b1001110 &
b1001110 )
b1001110 +
b1001110 ,
1"
#1600000
0"
#1610000
b101110111010 !
b101110111010 '
b101110111010 (
b1001111 &
b1001111 )
b1001111 +
b1001111 ,
1"
#1620000
0"
#1630000
b101111000101 !
b101111000101 '
b101111000101 (
b1010000 &
b1010000 )
b1010000 +
b1010000 ,
1"
#1640000
0"
#1650000
b101111010000 !
b101111010000 '
b101111010000 (
b1010001 &
b1010001 )
b1010001 +
b1010001 ,
1"
#1660000
0"
#1670000
b101111011011 !
b101111011011 '
b101111011011 (
b1010010 &
b1010010 )
b1010010 +
b1010010 ,
1"
#1680000
0"
#1690000
b101111100110 !
b101111100110 '
b101111100110 (
b1010011 &
b1010011 )
b1010011 +
b1010011 ,
1"
#1700000
0"
#1710000
b101111110001 !
b101111110001 '
b101111110001 (
b1010100 &
b1010100 )
b1010100 +
b1010100 ,
1"
#1720000
0"
#1730000
b101111111100 !
b101111111100 '
b101111111100 (
b1010101 &
b1010101 )
b1010101 +
b1010101 ,
1"
#1740000
0"
#1750000
b110000000110 !
b110000000110 '
b110000000110 (
b1010110 &
b1010110 )
b1010110 +
b1010110 ,
1"
#1760000
0"
#1770000
b110000010001 !
b110000010001 '
b110000010001 (
b1010111 &
b1010111 )
b1010111 +
b1010111 ,
1"
#1780000
0"
#1790000
b110000011100 !
b110000011100 '
b110000011100 (
b1011000 &
b1011000 )
b1011000 +
b1011000 ,
1"
#1800000
0"
#1810000
b110000100111 !
b110000100111 '
b110000100111 (
b1011001 &
b1011001 )
b1011001 +
b1011001 ,
1"
#1820000
0"
#1830000
b110000110010 !
b110000110010 '
b110000110010 (
b1011010 &
b1011010 )
b1011010 +
b1011010 ,
1"
#1840000
0"
#1850000
b110000111100 !
b110000111100 '
b110000111100 (
b1011011 &
b1011011 )
b1011011 +
b1011011 ,
1"
#1860000
0"
#1870000
b110001000111 !
b110001000111 '
b110001000111 (
b1011100 &
b1011100 )
b1011100 +
b1011100 ,
1"
#1880000
0"
#1890000
b110001010010 !
b110001010010 '
b110001010010 (
b1011101 &
b1011101 )
b1011101 +
b1011101 ,
1"
#1900000
0"
#1910000
b110001011100 !
b110001011100 '
b110001011100 (
b1011110 &
b1011110 )
b1011110 +
b1011110 ,
1"
#1920000
0"
#1930000
b110001100111 !
b110001100111 '
b110001100111 (
b1011111 &
b1011111 )
b1011111 +
b1011111 ,
1"
#1940000
0"
#1950000
b110001110001 !
b110001110001 '
b110001110001 (
b1100000 &
b1100000 )
b1100000 +
b1100000 ,
1"
#1960000
0"
#1970000
b110001111011 !
b110001111011 '
b110001111011 (
b1100001 &
b1100001 )
b1100001 +
b1100001 ,
1"
#1980000
0"
#1990000
b110010000110 !
b110010000110 '
b110010000110 (
b1100010 &
b1100010 )
b1100010 +
b1100010 ,
1"
#2000000
0"
#2010000
b110010010000 !
b110010010000 '
b110010010000 (
b1100011 &
b1100011 )
b1100011 +
b1100011 ,
1"
#2020000
0"
#2030000
b110010011010 !
b110010011010 '
b110010011010 (
b1100100 &
b1100100 )
b1100100 +
b1100100 ,
1"
#2040000
0"
#2050000
b110010100101 !
b110010100101 '
b110010100101 (
b1100101 &
b1100101 )
b1100101 +
b1100101 ,
1"
#2060000
0"
#2070000
b110010101111 !
b110010101111 '
b110010101111 (
b1100110 &
b1100110 )
b1100110 +
b1100110 ,
1"
#2080000
0"
#2090000
b110010111001 !
b110010111001 '
b110010111001 (
b1100111 &
b1100111 )
b1100111 +
b1100111 ,
1"
#2100000
0"
#2110000
b110011000011 !
b110011000011 '
b110011000011 (
b1101000 &
b1101000 )
b1101000 +
b1101000 ,
1"
#2120000
0"
#2130000
b110011001101 !
b110011001101 '
b110011001101 (
b1101001 &
b1101001 )
b1101001 +
b1101001 ,
1"
#2140000
0"
#2150000
b110011010111 !
b110011010111 '
b110011010111 (
b1101010 &
b1101010 )
b1101010 +
b1101010 ,
1"
#2160000
0"
#2170000
b110011100001 !
b110011100001 '
b110011100001 (
b1101011 &
b1101011 )
b1101011 +
b1101011 ,
1"
#2180000
0"
#2190000
b110011101011 !
b110011101011 '
b110011101011 (
b1101100 &
b1101100 )
b1101100 +
b1101100 ,
1"
#2200000
0"
#2210000
b110011110101 !
b110011110101 '
b110011110101 (
b1101101 &
b1101101 )
b1101101 +
b1101101 ,
1"
#2220000
0"
#2230000
b110011111111 !
b110011111111 '
b110011111111 (
b1101110 &
b1101110 )
b1101110 +
b1101110 ,
1"
#2240000
0"
#2250000
b110100001001 !
b110100001001 '
b110100001001 (
b1101111 &
b1101111 )
b1101111 +
b1101111 ,
1"
#2260000
0"
#2270000
b110100010010 !
b110100010010 '
b110100010010 (
b1110000 &
b1110000 )
b1110000 +
b1110000 ,
1"
#2280000
0"
#2290000
b110100011100 !
b110100011100 '
b110100011100 (
b1110001 &
b1110001 )
b1110001 +
b1110001 ,
1"
#2300000
0"
#2310000
b110100100110 !
b110100100110 '
b110100100110 (
b1110010 &
b1110010 )
b1110010 +
b1110010 ,
1"
#2320000
0"
#2330000
b110100101111 !
b110100101111 '
b110100101111 (
b1110011 &
b1110011 )
b1110011 +
b1110011 ,
1"
#2340000
0"
#2350000
b110100111001 !
b110100111001 '
b110100111001 (
b1110100 &
b1110100 )
b1110100 +
b1110100 ,
1"
#2360000
0"
#2370000
b110101000010 !
b110101000010 '
b110101000010 (
b1110101 &
b1110101 )
b1110101 +
b1110101 ,
1"
#2380000
0"
#2390000
b110101001100 !
b110101001100 '
b110101001100 (
b1110110 &
b1110110 )
b1110110 +
b1110110 ,
1"
#2400000
0"
#2410000
b110101010101 !
b110101010101 '
b110101010101 (
b1110111 &
b1110111 )
b1110111 +
b1110111 ,
1"
#2420000
0"
#2430000
b110101011111 !
b110101011111 '
b110101011111 (
b1111000 &
b1111000 )
b1111000 +
b1111000 ,
1"
#2440000
0"
#2450000
b110101101000 !
b110101101000 '
b110101101000 (
b1111001 &
b1111001 )
b1111001 +
b1111001 ,
1"
#2460000
0"
#2470000
b110101110001 !
b110101110001 '
b110101110001 (
b1111010 &
b1111010 )
b1111010 +
b1111010 ,
1"
#2480000
0"
#2490000
b110101111010 !
b110101111010 '
b110101111010 (
b1111011 &
b1111011 )
b1111011 +
b1111011 ,
1"
#2500000
0"
#2510000
b110110000011 !
b110110000011 '
b110110000011 (
b1111100 &
b1111100 )
b1111100 +
b1111100 ,
1"
#2520000
0"
#2530000
b110110001100 !
b110110001100 '
b110110001100 (
b1111101 &
b1111101 )
b1111101 +
b1111101 ,
1"
#2540000
0"
#2550000
b110110010101 !
b110110010101 '
b110110010101 (
b1111110 &
b1111110 )
b1111110 +
b1111110 ,
1"
#2560000
0"
#2570000
b110110011110 !
b110110011110 '
b110110011110 (
b1111111 &
b1111111 )
b1111111 +
b1111111 ,
1"
#2580000
0"
#2590000
b110110100111 !
b110110100111 '
b110110100111 (
b10000000 &
b10000000 )
b10000000 +
b10000000 ,
1"
#2600000
0"
#2610000
b110110110000 !
b110110110000 '
b110110110000 (
b10000001 &
b10000001 )
b10000001 +
b10000001 ,
1"
#2620000
0"
#2630000
b110110111001 !
b110110111001 '
b110110111001 (
b10000010 &
b10000010 )
b10000010 +
b10000010 ,
1"
#2640000
0"
#2650000
b110111000010 !
b110111000010 '
b110111000010 (
b10000011 &
b10000011 )
b10000011 +
b10000011 ,
1"
#2660000
0"
#2670000
b110111001010 !
b110111001010 '
b110111001010 (
b10000100 &
b10000100 )
b10000100 +
b10000100 ,
1"
#2680000
0"
#2690000
b110111010011 !
b110111010011 '
b110111010011 (
b10000101 &
b10000101 )
b10000101 +
b10000101 ,
1"
#2700000
0"
#2710000
b110111011100 !
b110111011100 '
b110111011100 (
b10000110 &
b10000110 )
b10000110 +
b10000110 ,
1"
#2720000
0"
#2730000
b110111100100 !
b110111100100 '
b110111100100 (
b10000111 &
b10000111 )
b10000111 +
b10000111 ,
1"
#2740000
0"
#2750000
b110111101101 !
b110111101101 '
b110111101101 (
b10001000 &
b10001000 )
b10001000 +
b10001000 ,
1"
#2760000
0"
#2770000
b110111110101 !
b110111110101 '
b110111110101 (
b10001001 &
b10001001 )
b10001001 +
b10001001 ,
1"
#2780000
0"
#2790000
b110111111101 !
b110111111101 '
b110111111101 (
b10001010 &
b10001010 )
b10001010 +
b10001010 ,
1"
#2800000
0"
#2810000
b111000000110 !
b111000000110 '
b111000000110 (
b10001011 &
b10001011 )
b10001011 +
b10001011 ,
1"
#2820000
0"
#2830000
b111000001110 !
b111000001110 '
b111000001110 (
b10001100 &
b10001100 )
b10001100 +
b10001100 ,
1"
#2840000
0"
#2850000
b111000010110 !
b111000010110 '
b111000010110 (
b10001101 &
b10001101 )
b10001101 +
b10001101 ,
1"
#2860000
0"
#2870000
b111000011110 !
b111000011110 '
b111000011110 (
b10001110 &
b10001110 )
b10001110 +
b10001110 ,
1"
#2880000
0"
#2890000
b111000100110 !
b111000100110 '
b111000100110 (
b10001111 &
b10001111 )
b10001111 +
b10001111 ,
1"
#2900000
0"
#2910000
b111000101110 !
b111000101110 '
b111000101110 (
b10010000 &
b10010000 )
b10010000 +
b10010000 ,
1"
#2920000
0"
#2930000
b111000110110 !
b111000110110 '
b111000110110 (
b10010001 &
b10010001 )
b10010001 +
b10010001 ,
1"
#2940000
0"
#2950000
b111000111110 !
b111000111110 '
b111000111110 (
b10010010 &
b10010010 )
b10010010 +
b10010010 ,
1"
#2960000
0"
#2970000
b111001000110 !
b111001000110 '
b111001000110 (
b10010011 &
b10010011 )
b10010011 +
b10010011 ,
1"
#2980000
0"
#2990000
b111001001110 !
b111001001110 '
b111001001110 (
b10010100 &
b10010100 )
b10010100 +
b10010100 ,
1"
#3000000
0"
#3010000
b111001010101 !
b111001010101 '
b111001010101 (
b10010101 &
b10010101 )
b10010101 +
b10010101 ,
1"
#3020000
0"
#3030000
b111001011101 !
b111001011101 '
b111001011101 (
b10010110 &
b10010110 )
b10010110 +
b10010110 ,
1"
#3040000
0"
#3050000
b111001100101 !
b111001100101 '
b111001100101 (
b10010111 &
b10010111 )
b10010111 +
b10010111 ,
1"
#3060000
0"
#3070000
b111001101100 !
b111001101100 '
b111001101100 (
b10011000 &
b10011000 )
b10011000 +
b10011000 ,
1"
#3080000
0"
#3090000
b111001110100 !
b111001110100 '
b111001110100 (
b10011001 &
b10011001 )
b10011001 +
b10011001 ,
1"
#3100000
0"
#3110000
b111001111011 !
b111001111011 '
b111001111011 (
b10011010 &
b10011010 )
b10011010 +
b10011010 ,
1"
#3120000
0"
#3130000
b111010000010 !
b111010000010 '
b111010000010 (
b10011011 &
b10011011 )
b10011011 +
b10011011 ,
1"
#3140000
0"
#3150000
b111010001010 !
b111010001010 '
b111010001010 (
b10011100 &
b10011100 )
b10011100 +
b10011100 ,
1"
#3160000
0"
#3170000
b111010010001 !
b111010010001 '
b111010010001 (
b10011101 &
b10011101 )
b10011101 +
b10011101 ,
1"
#3180000
0"
#3190000
b111010011000 !
b111010011000 '
b111010011000 (
b10011110 &
b10011110 )
b10011110 +
b10011110 ,
1"
#3200000
0"
#3210000
b111010011111 !
b111010011111 '
b111010011111 (
b10011111 &
b10011111 )
b10011111 +
b10011111 ,
1"
#3220000
0"
#3230000
b111010100110 !
b111010100110 '
b111010100110 (
b10100000 &
b10100000 )
b10100000 +
b10100000 ,
1"
#3240000
0"
#3250000
b111010101101 !
b111010101101 '
b111010101101 (
b10100001 &
b10100001 )
b10100001 +
b10100001 ,
1"
#3260000
0"
#3270000
b111010110100 !
b111010110100 '
b111010110100 (
b10100010 &
b10100010 )
b10100010 +
b10100010 ,
1"
#3280000
0"
#3290000
b111010111011 !
b111010111011 '
b111010111011 (
b10100011 &
b10100011 )
b10100011 +
b10100011 ,
1"
#3300000
0"
#3310000
b111011000001 !
b111011000001 '
b111011000001 (
b10100100 &
b10100100 )
b10100100 +
b10100100 ,
1"
#3320000
0"
#3330000
b111011001000 !
b111011001000 '
b111011001000 (
b10100101 &
b10100101 )
b10100101 +
b10100101 ,
1"
#3340000
0"
#3350000
b111011001111 !
b111011001111 '
b111011001111 (
b10100110 &
b10100110 )
b10100110 +
b10100110 ,
1"
#3360000
0"
#3370000
b111011010101 !
b111011010101 '
b111011010101 (
b10100111 &
b10100111 )
b10100111 +
b10100111 ,
1"
#3380000
0"
#3390000
b111011011100 !
b111011011100 '
b111011011100 (
b10101000 &
b10101000 )
b10101000 +
b10101000 ,
1"
#3400000
0"
#3410000
b111011100010 !
b111011100010 '
b111011100010 (
b10101001 &
b10101001 )
b10101001 +
b10101001 ,
1"
#3420000
0"
#3430000
b111011101000 !
b111011101000 '
b111011101000 (
b10101010 &
b10101010 )
b10101010 +
b10101010 ,
1"
#3440000
0"
#3450000
b111011101111 !
b111011101111 '
b111011101111 (
b10101011 &
b10101011 )
b10101011 +
b10101011 ,
1"
#3460000
0"
#3470000
b111011110101 !
b111011110101 '
b111011110101 (
b10101100 &
b10101100 )
b10101100 +
b10101100 ,
1"
#3480000
0"
#3490000
b111011111011 !
b111011111011 '
b111011111011 (
b10101101 &
b10101101 )
b10101101 +
b10101101 ,
1"
#3500000
0"
#3510000
b111100000001 !
b111100000001 '
b111100000001 (
b10101110 &
b10101110 )
b10101110 +
b10101110 ,
1"
#3520000
0"
#3530000
b111100000111 !
b111100000111 '
b111100000111 (
b10101111 &
b10101111 )
b10101111 +
b10101111 ,
1"
#3540000
0"
#3550000
b111100001101 !
b111100001101 '
b111100001101 (
b10110000 &
b10110000 )
b10110000 +
b10110000 ,
1"
#3560000
0"
#3570000
b111100010011 !
b111100010011 '
b111100010011 (
b10110001 &
b10110001 )
b10110001 +
b10110001 ,
1"
#3580000
0"
#3590000
b111100011001 !
b111100011001 '
b111100011001 (
b10110010 &
b10110010 )
b10110010 +
b10110010 ,
1"
#3600000
0"
#3610000
b111100011111 !
b111100011111 '
b111100011111 (
b10110011 &
b10110011 )
b10110011 +
b10110011 ,
1"
#3620000
0"
#3630000
b111100100100 !
b111100100100 '
b111100100100 (
b10110100 &
b10110100 )
b10110100 +
b10110100 ,
1"
#3640000
0"
#3650000
b111100101010 !
b111100101010 '
b111100101010 (
b10110101 &
b10110101 )
b10110101 +
b10110101 ,
1"
#3660000
0"
#3670000
b111100110000 !
b111100110000 '
b111100110000 (
b10110110 &
b10110110 )
b10110110 +
b10110110 ,
1"
#3680000
0"
#3690000
b111100110101 !
b111100110101 '
b111100110101 (
b10110111 &
b10110111 )
b10110111 +
b10110111 ,
1"
#3700000
0"
#3710000
b111100111010 !
b111100111010 '
b111100111010 (
b10111000 &
b10111000 )
b10111000 +
b10111000 ,
1"
#3720000
0"
#3730000
b111101000000 !
b111101000000 '
b111101000000 (
b10111001 &
b10111001 )
b10111001 +
b10111001 ,
1"
#3740000
0"
#3750000
b111101000101 !
b111101000101 '
b111101000101 (
b10111010 &
b10111010 )
b10111010 +
b10111010 ,
1"
#3760000
0"
#3770000
b111101001010 !
b111101001010 '
b111101001010 (
b10111011 &
b10111011 )
b10111011 +
b10111011 ,
1"
#3780000
0"
#3790000
b111101001111 !
b111101001111 '
b111101001111 (
b10111100 &
b10111100 )
b10111100 +
b10111100 ,
1"
#3800000
0"
#3810000
b111101010100 !
b111101010100 '
b111101010100 (
b10111101 &
b10111101 )
b10111101 +
b10111101 ,
1"
#3820000
0"
#3830000
b111101011001 !
b111101011001 '
b111101011001 (
b10111110 &
b10111110 )
b10111110 +
b10111110 ,
1"
#3840000
0"
#3850000
b111101011110 !
b111101011110 '
b111101011110 (
b10111111 &
b10111111 )
b10111111 +
b10111111 ,
1"
#3860000
0"
#3870000
b111101100011 !
b111101100011 '
b111101100011 (
b11000000 &
b11000000 )
b11000000 +
b11000000 ,
1"
#3880000
0"
#3890000
b111101101000 !
b111101101000 '
b111101101000 (
b11000001 &
b11000001 )
b11000001 +
b11000001 ,
1"
#3900000
0"
#3910000
b111101101101 !
b111101101101 '
b111101101101 (
b11000010 &
b11000010 )
b11000010 +
b11000010 ,
1"
#3920000
0"
#3930000
b111101110001 !
b111101110001 '
b111101110001 (
b11000011 &
b11000011 )
b11000011 +
b11000011 ,
1"
#3940000
0"
#3950000
b111101110110 !
b111101110110 '
b111101110110 (
b11000100 &
b11000100 )
b11000100 +
b11000100 ,
1"
#3960000
0"
#3970000
b111101111010 !
b111101111010 '
b111101111010 (
b11000101 &
b11000101 )
b11000101 +
b11000101 ,
1"
#3980000
0"
