flipflopD/flipflopD.v
module ffd (
    input wire d_in,
    input wire clk,
    input wire rst_in,
    output reg q_out
);

    always @(posedge clk) begin
        if (rst_in) begin
            q_out <= 0;
        end else begin
            q_out <= d_in;
        end
    end

endmodule

05-flipflopD/flipflopD_tb.v
`include "flipflopD.v"
`timescale 1ns / 1ps

module tb_flipflopD;

    // Declaración de señales
    reg clk = 0;          // Reloj
    reg rst_in;        // Reset asíncrono
    reg d_in;           // Entrada D
    wire q_out;          // Salida Q

    // Instanciamos el DUT (Device Under Test)
    ffd dut (
        .clk(clk),
        .rst_in(rst_in),
        .d_in(d_in),
        .q_out(q_out)
    );

    // Dump de señales para GTKWave
    initial begin
        $dumpfile("flipflopD.vcd");
        $dumpvars(0, tb_flipflopD);
    end

    // Generador de reloj: 50 MHz → período de 20 ns
    always #10 clk = ~clk;

    // Generación de señales de prueba
    initial begin
        // Inicializamos las señales
        rst_in = 1; d_in = 0; // Reset activo, salida debe ser 0
        #20 rst_in = 0; // Desactivamos el reset

        // Cambios en las señales para probar el circuito
        #20 d_in = 1; // Entrada D en 1, salida Q debe ser 1
        #20 d_in = 0; // Entrada D en 0, salida Q debe ser 0
        #20 d_in = 1; // Entrada D en 1, salida Q debe ser 1
        #20 d_in = 0; // Entrada D en 0, salida Q debe ser 0

        // Activamos el reset nuevamente
        #20 rst_in = 1; // Reset activo, salida debe ser 0
        #20 rst_in = 0; // Desactivamos el reset

        // Finalizamos la simulación
        #100 $finish;
        
    end
endmodule

flipflopD/flipflopD.vcd
$date
	Mon Jun 23 00:16:19 2025
$end
$version
	Icarus Verilog
$end
$timescale
	1ps
$end
$scope module tb_flipflopD $end
$var wire 1 ! q_out $end
$var reg 1 " clk $end
$var reg 1 # d_in $end
$var reg 1 $ rst_in $end
$scope module dut $end
$var wire 1 " clk $end
$var wire 1 # d_in $end
$var wire 1 $ rst_in $end
$var reg 1 ! q_out $end
$upscope $end
$upscope $end
$enddefinitions $end
#0
$dumpvars
1$
0#
0"
x!
$end
#10000
0!
1"
#20000
0"
0$
#30000
1"
#40000
0"
1#
#50000
1!
1"
#60000
0"
0#
#70000
0!
1"
#80000
0"
1#
#90000
1!
1"
#100000
0"
0#
#110000
0!
1"
#120000
0"
1$
#130000
1"
#140000
0"
0$
