registro-sipo/sipo.v
module sipo #(
    parameter DATA_WIDTH = 4,
    parameter CLOCK_EDGE = 1 // 1 para flanco ascendente, 0 para descendente
)(
    input wire d_in,
    output wire [DATA_WIDTH-1:0] q_out,
    input wire out_enable_in,
    input wire rst,
    input wire clk
);
    reg [DATA_WIDTH-1:0] d_reg;
    generate
        if (CLOCK_EDGE == 1) begin : posedge_clk
            always @ (posedge clk or posedge rst)
                begin
                    if (rst) begin
                        d_reg <= {DATA_WIDTH{1'b0}};
                    end else begin
                        d_reg <= {d_reg[DATA_WIDTH-2:0], d_in};
                    end
                end
        end else begin : negedge_clk
            always @ (negedge clk or posedge rst)
                begin
                    if (rst) begin
                        d_reg <= {DATA_WIDTH{1'b0}};
                    end else begin
                        d_reg <= {d_reg[DATA_WIDTH-2:0], d_in};
                    end
                end
        end
    endgenerate

    assign q_out = out_enable_in ? d_reg : 1'bz;

endmodule

10-registro-sipo/sipo_tb.v
`include "sipo.v"
`timescale 1ns / 1ps


module sipo_tb;
    // Declaración de señales
    reg d_in;
    wire [3:0] q_out;
    reg out_enable_in;
    reg rst;
    reg clk = 0;

    reg [3:0] d_reg = 4'b1001; // Registro interno para verificar el estado
    integer i;

    sipo #(
        .DATA_WIDTH(4),
        .CLOCK_EDGE(1)
    ) dut (
        .d_in(d_in),
        .q_out(q_out),
        .out_enable_in(out_enable_in),
        .rst(rst),
        .clk(clk)
    );

    always #10 clk = ~clk;

    initial begin
        $dumpfile("sipo.vcd");
        $dumpvars(0, sipo_tb);
    end

    initial begin
        out_enable_in = 1;
        rst = 1; // Activar el reset inicialmente
        #20; // Espera para permitir que el reset se aplique
        rst = 0;

        #20 
        for (i = 0; i < 4; i = i + 1) begin
            d_in = d_reg[i];
            #20; // Espera para permitir que el registro se actualice
        end
        #80
        rst = 1; // Activar el reset
        #20;
        rst = 0; // Desactivar el reset
        out_enable_in = 0; // Desactivar la salida

        #40 $finish;
    end
endmodule

registro-sipo/sipo.vcd
$date
	Wed Aug  6 20:03:30 2025
$end
$version
	Icarus Verilog
$end
$timescale
	1ps
$end
$scope module sipo_tb $end
$var wire 4 ! q_out [3:0] $end
$var reg 1 " clk $end
$var reg 1 # d_in $end
$var reg 4 $ d_reg [3:0] $end
$var reg 1 % out_enable_in $end
$var reg 1 & rst $end
$var integer 32 ' i [31:0] $end
$scope module dut $end
$var wire 1 " clk $end
$var wire 1 # d_in $end
$var wire 1 % out_enable_in $end
$var wire 1 & rst $end
$var wire 4 ( q_out [3:0] $end
$var reg 4 ) d_reg [3:0] $end
$scope begin posedge_clk $end
$upscope $end
$upscope $end
$upscope $end
$enddefinitions $end
#0
$dumpvars
b0 )
b0 (
bx '
1&
1%
b1001 $
x#
0"
b0 !
$end
#10000
1"
#20000
0"
0&
#30000
b0x !
b0x (
b0x )
1"
#40000
0"
1#
b0 '
#50000
b0x1 !
b0x1 (
b0x1 )
1"
#60000
0"
0#
b1 '
#70000
b0x10 !
b0x10 (
b0x10 )
1"
#80000
0"
b10 '
#90000
bx100 !
bx100 (
bx100 )
1"
#100000
0"
1#
b11 '
#110000
b1001 !
b1001 (
b1001 )
1"
#120000
0"
b100 '
#130000
b11 !
b11 (
b11 )
1"
#140000
0"
#150000
b111 !
b111 (
b111 )
1"
#160000
0"
#170000
b1111 !
b1111 (
b1111 )
1"
#180000
0"
#190000
1"
#200000
b0 !
b0 (
b0 )
0"
1&
#210000
1"
#220000
b0z !
b0z (
0"
0%
0&
#230000
b1 )
1"
#240000
0"
#250000
b11 )
1"
