registro_pipo/pipo.v
module pipo #(
    parameter DATA_WIDTH = 8,
    parameter CLOCK_EDGE = 1 // 1 para flanco ascendente, 0 para descendente
)(
    input wire [DATA_WIDTH-1:0] d_in,
    output reg [DATA_WIDTH-1:0] q_out,
    input wire out_enable_in,
    input wire rst,
    input wire clk,
    input wire clk_enable
);
    reg [DATA_WIDTH-1:0] d_reg;

    always @ (posedge clk or posedge rst)
        begin
            if (rst) begin
                d_reg <= {DATA_WIDTH{1'b0}};
            end else if (clk_enable) begin
                d_reg <= d_in;
            end
        end

    assign q_out = out_enable_in ? d_reg : {DATA_WIDTH{1'bz}};

endmodule

07-registro_pipo/pipo_tb.v
`include "pipo.v"
`timescale 1ns / 1ps


module pipo_tb;
    // Declaración de señales
    reg [7:0] d_in;
    wire [7:0] q_out;
    reg out_enable_in;
    reg rst;
    reg clk = 0;
    reg clk_enable;

    pipo #(
        .DATA_WIDTH(8),
        .CLOCK_EDGE(1)
    ) dut (
        .d_in(d_in),
        .q_out(q_out),
        .out_enable_in(out_enable_in),
        .rst(rst),
        .clk(clk),
        .clk_enable(clk_enable)
    );

    always #10 clk = ~clk;

    initial begin
        $dumpfile("pipo.vcd");
        $dumpvars(0, pipo_tb);
    end

    initial begin
        clk_enable = 1;
        out_enable_in = 1;
        rst = 0;

        #20 d_in = 8'b10101010;

        #20 clk_enable = 0;
        d_in = 8'b00000000;

        #80 clk_enable = 1;
        d_in = 8'b11110000;

        #20 clk_enable = 0;

        #20 rst = 1;

        #40 out_enable_in = 0;

        #40 $finish;
    end
endmodule

07-registro_pipo/pipo.vcd
$date
	Thu Jul 31 12:20:34 2025
$end
$version
	Icarus Verilog
$end
$timescale
	1ps
$end
$scope module pipo_tb $end
$var wire 8 ! q_out [7:0] $end
$var reg 1 " clk $end
$var reg 1 # clk_enable $end
$var reg 8 $ d_in [7:0] $end
$var reg 1 % out_enable_in $end
$var reg 1 & rst $end
$scope module dut $end
$var wire 1 " clk $end
$var wire 1 # clk_enable $end
$var wire 8 ' d_in [7:0] $end
$var wire 1 % out_enable_in $end
$var wire 1 & rst $end
$var wire 8 ( q_out [7:0] $end
$var reg 8 ) d_reg [7:0] $end
$upscope $end
$upscope $end
$enddefinitions $end
#0
$dumpvars
bx )
bx (
bx '
0&
1%
bx $
1#
0"
bx !
$end
#10000
1"
#20000
0"
b10101010 $
b10101010 '
#30000
b10101010 !
b10101010 (
b10101010 )
1"
#40000
0"
b0 $
b0 '
0#
#50000
1"
#60000
0"
#70000
1"
#80000
0"
#90000
1"
#100000
0"
#110000
1"
#120000
0"
b11110000 $
b11110000 '
1#
#130000
b11110000 !
b11110000 (
b11110000 )
1"
#140000
0"
0#
#150000
1"
#160000
b0 !
b0 (
b0 )
0"
1&
#170000
1"
#180000
0"
#190000
1"
#200000
bz !
bz (
0"
0%
