contador_universal/contador_universal.v
module contador_universal #(
    parameter N = 4,               // Cantidad de bits
    parameter MOD = 16,              // Módulo del contador
    parameter CLK_EDGE = 1         // 1 para flanco ascendente, 0 para descendente
)(
    input wire clk,
    input wire rst,                // Reset asincrónico
    input wire load_in,              // Carga por D
    input wire [N-1:0] d_in,         // Valor de carga
    input wire out_enable_in,        // Habilita la salida
    input wire counter_enable_in,    // Habilita el conteo
    input wire count_up_in,          // 1 = up, 0 = down
    input wire clk_edge_in,
    output wire [N-1:0] q_out,        // Salida del contador
    output reg terminal_count_out     // Indica fin de cuenta
);
    reg  [N-1:0] r_reg = {N{1'b0}}; // Registro del contador
    reg  [N-1:0] r_load = {N{1'b1}};
    wire [N-1:0] r_next;


    always @ (posedge clk, posedge rst) 
        begin
            if(rst) begin
                r_reg <= {N{1'b0}};
                terminal_count_out <= 1'b0; // Resetear la señal de terminal count
            end else if (load_in && out_enable_in) begin
                r_reg <= d_in;
                r_load <= d_in;
                terminal_count_out <= 1'b0; // Resetear la señal de terminal count
            end else if (counter_enable_in) begin
                    r_reg <= r_next;
                    if (r_reg == {N{1'b0}} && !count_up_in) begin
                        terminal_count_out <= 1'b1;
                        r_reg <= r_load;
                    end else if (r_reg == MOD - 1 && count_up_in) begin
                        terminal_count_out <= 1'b1;
                        r_reg <= {N{1'b0}};
                    end
                end
        end

    assign r_next = count_up_in ? (r_reg + 1) : (r_reg - 1);

    assign q_out = out_enable_in ? r_reg : {N{1'bz}};

endmodule

contador_universal/contador_universal_tb.v
`include "contador_universal.v"
`timescale 1ns / 1ps

module tb_contador_universal;

    // Declaración de señales
    reg clk = 0;
    reg rst;
    reg load_in;
    reg [3:0] d_in;
    reg out_enable_in;
    reg counter_enable_in;
    reg count_up_in;
    wire [3:0] q_out;
    wire terminal_count_out;

    // Instanciamos el DUT (Device Under Test)
    contador_universal #(
        .N(4),
        .MOD(16),
        .CLK_EDGE(1)
    ) dut (
        .clk(clk),
        .rst(rst),
        .load_in(load_in),
        .d_in(d_in),
        .out_enable_in(out_enable_in),
        .counter_enable_in(counter_enable_in),
        .count_up_in(count_up_in),
        .q_out(q_out),
        .terminal_count_out(terminal_count_out)
    );

    always #10 clk = ~clk; // Generador de reloj: 50 MHz → período de 20 ns

    // Dump de señales para GTKWave
    initial begin
        $dumpfile("contador_universal.vcd");
        $dumpvars(0, tb_contador_universal);
    end

    // Estímulo inicial
    initial begin
        // Valores iniciales
        load_in = 0;
        d_in = 4'b0000;
        out_enable_in = 1;
        counter_enable_in = 1;
        count_up_in = 1;

        #60 rst = 1;
        // Liberar el reset
        #15 rst = 0;

        // Cargar un valor
        #20 load_in = 1; d_in = 4'b1010;
        #20 load_in = 0;

        // Deshabilitar el contador
        #80 count_up_in = 0;

        // Finalizar la simulación
        #60 $finish;
    end
endmodule

06-contador_universal/contador_universal.vcd
$date
	Wed Jul 23 20:02:25 2025
$end
$version
	Icarus Verilog
$end
$timescale
	1ps
$end
$scope module tb_contador_universal $end
$var wire 1 ! terminal_count_out $end
$var wire 4 " q_out [3:0] $end
$var reg 1 # clk $end
$var reg 1 $ count_up_in $end
$var reg 1 % counter_enable_in $end
$var reg 4 & d_in [3:0] $end
$var reg 1 ' load_in $end
$var reg 1 ( out_enable_in $end
$var reg 1 ) rst $end
$scope module dut $end
$var wire 1 # clk $end
$var wire 1 * clk_edge_in $end
$var wire 1 $ count_up_in $end
$var wire 1 % counter_enable_in $end
$var wire 4 + d_in [3:0] $end
$var wire 1 ' load_in $end
$var wire 1 ( out_enable_in $end
$var wire 1 ) rst $end
$var wire 4 , r_next [3:0] $end
$var wire 4 - q_out [3:0] $end
$var reg 4 . r_load [3:0] $end
$var reg 4 / r_reg [3:0] $end
$var reg 1 ! terminal_count_out $end
$upscope $end
$upscope $end
$enddefinitions $end
#0
$dumpvars
b0 /
b1111 .
b0 -
b1 ,
b0 +
z*
x)
1(
0'
b0 &
1%
1$
0#
b0 "
x!
$end
#10000
b10 ,
b1 "
b1 -
b1 /
1#
#20000
0#
#30000
b11 ,
b10 "
b10 -
b10 /
1#
#40000
0#
#50000
b100 ,
b11 "
b11 -
b11 /
1#
#60000
b1 ,
b0 "
b0 -
0!
b0 /
0#
1)
#70000
1#
#75000
0)
#80000
0#
#90000
b10 ,
b1 "
b1 -
b1 /
1#
#95000
b1010 &
b1010 +
1'
#100000
0#
#110000
b1011 ,
b1010 "
b1010 -
b1010 .
b1010 /
1#
#115000
0'
#120000
0#
#130000
b1100 ,
b1011 "
b1011 -
b1011 /
1#
#140000
0#
#150000
b1101 ,
b1100 "
b1100 -
b1100 /
1#
#160000
0#
#170000
b1110 ,
b1101 "
b1101 -
b1101 /
1#
#180000
0#
#190000
b1111 ,
b1110 "
b1110 -
b1110 /
1#
#195000
b1101 ,
0$
#200000
0#
#210000
b1100 ,
b1101 "
b1101 -
b1101 /
1#
#220000
0#
#230000
b1011 ,
b1100 "
b1100 -
b1100 /
1#
#240000
0#
#250000
b1010 ,
b1011 "
b1011 -
b1011 /
1#
