registro-piso/piso.v
module piso #(
    parameter DATA_WIDTH = 4,
    parameter CLOCK_EDGE = 1 // 1 para flanco ascendente, 0 para descendente
)(
    input wire [DATA_WIDTH-1:0] d_in,
    output wire q_out,
    input wire out_enable_in,
    input wire rst,
    input wire clk,
    input wire clk_enable,
    input wire load_enable_in
);
    reg [DATA_WIDTH-1:0] d_reg;
    generate
        if (CLOCK_EDGE == 1) begin : posedge_clk
            always @ (posedge clk or posedge rst)
                begin
                    if (rst) begin
                        d_reg <= {DATA_WIDTH{1'b0}};
                    end else if (load_enable_in) begin
                        d_reg <= d_in;
                    end else if (clk_enable) begin
                        d_reg <= {d_reg[DATA_WIDTH-2:0], 1'b0};
                    end
                end
        end else begin : negedge_clk
            always @ (negedge clk or posedge rst)
                begin
                    if (rst) begin
                        d_reg <= {DATA_WIDTH{1'b0}};
                    end else if (load_enable_in) begin
                        d_reg <= d_in;
                    end else if (clk_enable) begin
                        d_reg <= {d_reg[DATA_WIDTH-2:0], 1'b0};
                    end
                end
        end
    endgenerate

    assign q_out = out_enable_in ? d_reg[DATA_WIDTH-1] : 1'bz;

endmodule

registro-piso/piso_tb.v
`include "piso.v"
`timescale 1ns / 1ps


module piso_tb;
    // Declaración de señales
    reg [3:0] d_in;
    wire q_out;
    reg out_enable_in;
    reg rst;
    reg clk = 0;
    reg clk_enable;
    reg load_enable_in;

    reg [3:0] d_reg = 4'b1001; // Registro interno para verificar el estado
    integer i;

    piso #(
        .DATA_WIDTH(4),
        .CLOCK_EDGE(1)
    ) dut (
        .d_in(d_in),
        .q_out(q_out),
        .out_enable_in(out_enable_in),
        .rst(rst),
        .clk(clk),
        .clk_enable(clk_enable),
        .load_enable_in(load_enable_in)
    );

    always #10 clk = ~clk;

    initial begin
        $dumpfile("piso.vcd");
        $dumpvars(0, piso_tb);
    end

    initial begin
        out_enable_in = 1;
        clk_enable = 1;
        rst = 1;
        #20 rst = 0; // Desactivar el reset
        load_enable_in = 1;
        d_in = d_reg; // Cargar el registro con el valor inicial
        #20;
        load_enable_in = 0;
        #240
        rst = 1; // Activar el reset
        #20;
        rst = 0; // Desactivar el reset
        out_enable_in = 0; // Desactivar la salida

        #40 $finish;
    end
endmodule

09-registro-piso/piso.vcd
$date
	Tue Aug  5 15:17:38 2025
$end
$version
	Icarus Verilog
$end
$timescale
	1ps
$end
$scope module piso_tb $end
$var wire 1 ! q_out $end
$var reg 1 " clk $end
$var reg 1 # clk_enable $end
$var reg 4 $ d_in [3:0] $end
$var reg 4 % d_reg [3:0] $end
$var reg 1 & load_enable_in $end
$var reg 1 ' out_enable_in $end
$var reg 1 ( rst $end
$scope module dut $end
$var wire 1 " clk $end
$var wire 1 # clk_enable $end
$var wire 4 ) d_in [3:0] $end
$var wire 1 & load_enable_in $end
$var wire 1 ' out_enable_in $end
$var wire 1 ( rst $end
$var wire 1 ! q_out $end
$var reg 4 * d_reg [3:0] $end
$scope begin posedge_clk $end
$upscope $end
$upscope $end
$upscope $end
$enddefinitions $end
#0
$dumpvars
b0 *
bx )
1(
1'
x&
b1001 %
bx $
1#
0"
0!
$end
#10000
1"
#20000
0"
b1001 $
b1001 )
1&
0(
#30000
1!
b1001 *
1"
#40000
0"
0&
#50000
0!
b10 *
1"
#60000
0"
#70000
b100 *
1"
#80000
0"
#90000
1!
b1000 *
1"
#100000
0"
#110000
0!
b0 *
1"
#120000
0"
#130000
1"
#140000
0"
#150000
1"
#160000
0"
#170000
1"
#180000
0"
#190000
1"
#200000
0"
#210000
1"
#220000
0"
#230000
1"
#240000
0"
#250000
1"
#260000
0"
#270000
1"
#280000
0"
1(
#290000
1"
#300000
z!
0"
0'
0(
