mux_8ch_nbits/mux8chNbits.v
module mux8chNbits #(
    parameter N = 4 // Number of bits per channel
    )(
    input wire [2:0] sel_in,
    input wire [N-1:0] data_in_0,
    input wire [N-1:0] data_in_1,
    input wire [N-1:0] data_in_2,
    input wire [N-1:0] data_in_3,
    input wire [N-1:0] data_in_4,
    input wire [N-1:0] data_in_5,
    input wire [N-1:0] data_in_6,
    input wire [N-1:0] data_in_7,
    output reg [N-1:0] data_out
);
    always @(*) begin
        case (sel_in)
            3'b000: data_out = data_in_0;
            3'b001: data_out = data_in_1;
            3'b010: data_out = data_in_2;
            3'b011: data_out = data_in_3;
            3'b100: data_out = data_in_4;
            3'b101: data_out = data_in_5;
            3'b110: data_out = data_in_6;
            3'b111: data_out = data_in_7;
            default: data_out = {N{1'b0}}; // Default case to avoid latches
        endcase
    end
endmodule

mux_8ch_nbits/mux8chNbits_tb.v
`include "mux8chNbits.v"
`timescale 1ns / 1ps

module tb_mux8chNbits;

    // Declaración de señales
    reg [2:0] sel_in;
    reg [3:0] data_in_0, data_in_1, data_in_2, data_in_3, data_in_4, data_in_5, data_in_6, data_in_7;
    wire [3:0] data_out;

    // Instanciamos el DUT (Device Under Test)
    mux8chNbits #(.N(4)) dut (
        .sel_in(sel_in),
        .data_in_0(data_in_0),
        .data_in_1(data_in_1),
        .data_in_2(data_in_2),
        .data_in_3(data_in_3),
        .data_in_4(data_in_4),
        .data_in_5(data_in_5),
        .data_in_6(data_in_6),
        .data_in_7(data_in_7),
        .data_out(data_out)
    );

    // Dump de señales para GTKWave
    initial begin
        $dumpfile("mux8chNbits.vcd");
        $dumpvars(0, tb_mux8chNbits);
    end

    // Generación de señales de prueba
    initial begin
        // Inicializamos las señales
        sel_in = 3'b000;
        data_in_0 = 4'b0000;
        data_in_1 = 4'b0001;
        data_in_2 = 4'b0010;
        data_in_3 = 4'b0011;
        data_in_4 = 4'b0100;
        data_in_5 = 4'b0101;
        data_in_6 = 4'b0110;
        data_in_7 = 4'b0111;

        #10; // Esperar un tiempo para observar la salida

        sel_in = 3'b001; // Seleccionar canal 1
        #10;

        sel_in = 3'b010; // Seleccionar canal 2
        #10;

        sel_in = 3'b011; // Seleccionar canal 3
        #10;

        sel_in = 3'b100; // Seleccionar canal 4
        #10;

        sel_in = 3'b101; // Seleccionar canal 5
        #10;

        sel_in = 3'b110; // Seleccionar canal 6
        #10;

        sel_in = 3'b111; // Seleccionar canal 7
        #10;

        sel_in = 3'b000; // Volver al canal 0
        #10;
    end
endmodule

02-mux_8ch_nbits/mux8chNbits.vcd
$date
	Tue Jul 15 22:02:31 2025
$end
$version
	Icarus Verilog
$end
$timescale
	1ps
$end
$scope module tb_mux8chNbits $end
$var wire 4 ! data_out [3:0] $end
$var reg 4 " data_in_0 [3:0] $end
$var reg 4 # data_in_1 [3:0] $end
$var reg 4 $ data_in_2 [3:0] $end
$var reg 4 % data_in_3 [3:0] $end
$var reg 4 & data_in_4 [3:0] $end
$var reg 4 ' data_in_5 [3:0] $end
$var reg 4 ( data_in_6 [3:0] $end
$var reg 4 ) data_in_7 [3:0] $end
$var reg 3 * sel_in [2:0] $end
$scope module dut $end
$var wire 4 + data_in_0 [3:0] $end
$var wire 4 , data_in_1 [3:0] $end
$var wire 4 - data_in_2 [3:0] $end
$var wire 4 . data_in_3 [3:0] $end
$var wire 4 / data_in_4 [3:0] $end
$var wire 4 0 data_in_5 [3:0] $end
$var wire 4 1 data_in_6 [3:0] $end
$var wire 4 2 data_in_7 [3:0] $end
$var wire 3 3 sel_in [2:0] $end
$var reg 4 4 data_out [3:0] $end
$upscope $end
$upscope $end
$enddefinitions $end
#0
$dumpvars
b0 4
b0 3
b111 2
b110 1
b101 0
b100 /
b11 .
b10 -
b1 ,
b0 +
b0 *
b111 )
b110 (
b101 '
b100 &
b11 %
b10 $
b1 #
b0 "
b0 !
$end
#10000
b1 !
b1 4
b1 *
b1 3
#20000
b10 !
b10 4
b10 *
b10 3
#30000
b11 !
b11 4
b11 *
b11 3
#40000
b100 !
b100 4
b100 *
b100 3
#50000
b101 !
b101 4
b101 *
b101 3
#60000
b110 !
b110 4
b110 *
b110 3
#70000
b111 !
b111 4
b111 *
b111 3
#80000
b0 !
b0 4
b0 *
b0 3
