08-registro_siso/siso.v
module siso #(
    parameter DATA_WIDTH = 4,
    parameter CLOCK_EDGE = 1 // 1 para flanco ascendente, 0 para descendente
)(
    input wire d_in,
    output wire q_out,
    input wire out_enable_in,
    input wire rst,
    input wire clk
);
    reg [DATA_WIDTH-1:0]d_reg;
    generate
        if (CLOCK_EDGE == 1) begin : posedge_clk
            always @ (posedge clk or posedge rst)
                begin
                    if (rst) begin
                        d_reg <= {DATA_WIDTH{1'b0}};
                    end else begin
                        d_reg <= {d_reg[DATA_WIDTH-2:0], d_in};
                    end
                end
        end else begin : negedge_clk
            always @ (negedge clk or posedge rst)
                begin
                    if (rst) begin
                        d_reg <= {DATA_WIDTH{1'b0}};
                    end else begin
                        d_reg <= {d_reg[DATA_WIDTH-2:0], d_in};
                    end
                end
        end
    endgenerate

    assign q_out = out_enable_in ? d_reg[DATA_WIDTH-1] : 1'bz;

endmodule

registro_siso/siso_tb.v
`include "siso.v"
`timescale 1ns / 1ps


module siso_tb;
    // Declaración de señales
    reg d_in;
    wire q_out;
    reg out_enable_in;
    reg rst;
    reg clk = 0;

    reg [3:0] d_reg = 4'b1001; // Registro interno para verificar el estado
    integer i;

    siso #(
        .DATA_WIDTH(4),
        .CLOCK_EDGE(1)
    ) dut (
        .d_in(d_in),
        .q_out(q_out),
        .out_enable_in(out_enable_in),
        .rst(rst),
        .clk(clk)
    );

    always #10 clk = ~clk;

    initial begin
        $dumpfile("siso.vcd");
        $dumpvars(0, siso_tb);
    end

    initial begin
        out_enable_in = 1;
        rst = 0;

        #20 
        for (i = 0; i < 4; i = i + 1) begin
            d_in = d_reg[i];
            #20; // Espera para permitir que el registro se actualice
        end
        d_in = 0; // Enviar un valor de 0 al final
        #80
        rst = 1; // Activar el reset
        #20;
        rst = 0; // Desactivar el reset
        out_enable_in = 0; // Desactivar la salida

        #40 $finish;
    end
endmodule

registro_siso/siso.vcd
$date
	Sat Aug  2 14:47:45 2025
$end
$version
	Icarus Verilog
$end
$timescale
	1ps
$end
$scope module siso_tb $end
$var wire 1 ! q_out $end
$var reg 1 " clk $end
$var reg 1 # d_in $end
$var reg 4 $ d_reg [3:0] $end
$var reg 1 % out_enable_in $end
$var reg 1 & rst $end
$var integer 32 ' i [31:0] $end
$scope module dut $end
$var wire 1 " clk $end
$var wire 1 # d_in $end
$var wire 1 % out_enable_in $end
$var wire 1 & rst $end
$var wire 1 ! q_out $end
$var reg 4 ( d_reg [3:0] $end
$scope begin posedge_clk $end
$upscope $end
$upscope $end
$upscope $end
$enddefinitions $end
#0
$dumpvars
bx (
bx '
0&
1%
b1001 $
x#
0"
x!
$end
#10000
1"
#20000
0"
1#
b0 '
#30000
bx1 (
1"
#40000
0"
0#
b1 '
#50000
bx10 (
1"
#60000
0"
b10 '
#70000
bx100 (
1"
#80000
0"
1#
b11 '
#90000
1!
b1001 (
1"
#100000
0"
0#
b100 '
#110000
0!
b10 (
1"
#120000
0"
#130000
b100 (
1"
#140000
0"
#150000
1!
b1000 (
1"
#160000
0"
#170000
0!
b0 (
1"
#180000
0"
1&
#190000
1"
#200000
z!
0"
0%
0&
